kuest_py_clob_client-0.34.5.dist-info/licenses/LICENSE
py_clob_client/__init__.py
py_clob_client/client.py
py_clob_client/clob_types.py
py_clob_client/config.py
py_clob_client/constants.py
py_clob_client/endpoints.py
py_clob_client/exceptions.py
py_clob_client/signer.py
py_clob_client/utilities.py
py_clob_client/headers/__init__.py
py_clob_client/headers/headers.py
py_clob_client/http_helpers/__init__.py
py_clob_client/http_helpers/helpers.py
py_clob_client/order_builder/__init__.py
py_clob_client/order_builder/builder.py
py_clob_client/order_builder/constants.py
py_clob_client/order_builder/helpers.py
py_clob_client/rfq/__init__.py
py_clob_client/rfq/rfq_client.py
py_clob_client/rfq/rfq_helpers.py
py_clob_client/rfq/rfq_types.py
py_clob_client/signing/__init__.py
py_clob_client/signing/eip712.py
py_clob_client/signing/hmac.py
py_clob_client/signing/model.py
tests/__init__.py
tests/test_utilities.py
tests/headers/__init__.py
tests/headers/test_headers.py
tests/http_helpers/__init__.py
tests/http_helpers/test_helpers.py
tests/order_builder/__init__.py
tests/order_builder/test_builder.py
tests/order_builder/test_helpers.py
tests/signing/__init__.py
tests/signing/test_eip712.py
tests/signing/test_hmac.py
kuest_py_clob_client-0.34.5.dist-info/METADATA
kuest_py_clob_client-0.34.5.dist-info/WHEEL
kuest_py_clob_client-0.34.5.dist-info/top_level.txt
kuest_py_clob_client-0.34.5.dist-info/RECORD
